llama_index/packs/node_parser_semantic_chunking/BUILD
llama_index/packs/node_parser_semantic_chunking/__init__.py
llama_index/packs/node_parser_semantic_chunking/base.py
llama_index_packs_node_parser-0.1.2.dist-info/METADATA
llama_index_packs_node_parser-0.1.2.dist-info/WHEEL
llama_index_packs_node_parser-0.1.2.dist-info/RECORD
