Metadata-Version: 2.1
Name: llama-index-packs-node-parser
Version: 0.1.2
Summary: llama-index packs node_parser integration
License: MIT
Keywords: chunk,chunking,embedding,node,parser,semantic
Author: Your Name
Author-email: you@example.com
Maintainer: jerryjliu
Requires-Python: >=3.8.1,<3.12
Classifier: License :: OSI Approved :: MIT License
Classifier: Programming Language :: Python :: 3
Classifier: Programming Language :: Python :: 3.9
Classifier: Programming Language :: Python :: 3.10
Classifier: Programming Language :: Python :: 3.11
Requires-Dist: llama-index-core (>=0.10.1,<0.11.0)
